{
    "schema":{
        "fields":[
            {
                "name":"index",
                "type":"integer"
            },
            {
                "name":"Variable Name",
                "type":"string"
            },
            {
                "name":"Type",
                "type":"string"
            },
            {
                "name":"Hash",
                "type":"string"
            },
            {
                "name":"Size (bytes)",
                "type":"integer"
            }
        ],
        "primaryKey":[
            "index"
        ],
        "pandas_version":"1.4.0"
    },
    "data":[
        {
            "index":0,
            "Variable Name":"LOG_FILE",
            "Type":"str",
            "Hash":"7b44836fb79ce22bc3d734d6403fc41f352186c203433948f766440cfa58d019",
            "Size (bytes)":76
        },
        {
            "index":1,
            "Variable Name":"ARCHIVE_FOLDER",
            "Type":"str",
            "Hash":"0eb3e36bfb24dcd9bb1d1bece1531216b59539a8fde17ee80224af0653c92aa3",
            "Size (bytes)":56
        },
        {
            "index":2,
            "Variable Name":"LOG_RETENTION_DAYS",
            "Type":"int",
            "Hash":"624b60c58c9d8bfb6ff1886c2fd605d2adeb6ea4da576068201b6c6958ce93f4",
            "Size (bytes)":28
        },
        {
            "index":3,
            "Variable Name":"BASE_DIR",
            "Type":"str",
            "Hash":"693436e4e64035f77d9fffe088be68070715867d185f0fdae29a09fb84a3e253",
            "Size (bytes)":76
        },
        {
            "index":4,
            "Variable Name":"configuration",
            "Type":"dict",
            "Hash":"017b754cb14d7eaf01a1ba5aec8a654fd8cd45de38cbfdf999e9314f2a44770e",
            "Size (bytes)":184
        },
        {
            "index":5,
            "Variable Name":"voter_rolls_data",
            "Type":"ndarray",
            "Hash":"98ad0623728a623bed876f8709db7570ba5ca973befe2d2979701b692c3c0c47",
            "Size (bytes)":128
        },
        {
            "index":6,
            "Variable Name":"past_election_results_data",
            "Type":"ndarray",
            "Hash":"f6163a0e806f6caed0716aa6b917ff9a0fc76e4756adcc3822e326adb2f5b9e1",
            "Size (bytes)":128
        }
    ]
}